[
  {"indirizzo abitazione": "Via Roma, 25, 35100 Padova PD", "lat": 45.4064, "lon": 11.8768},
  {"indirizzo abitazione": "Via del Santo, 15, 35100 Padova PD", "lat": 45.4020, "lon": 11.8850},
  {"indirizzo abitazione": "Corso del Popolo, 45, 35100 Padova PD", "lat": 45.4080, "lon": 11.8720},
  {"indirizzo abitazione": "Via Giotto, 12, 35100 Padova PD", "lat": 45.4050, "lon": 11.8800},
  {"indirizzo abitazione": "Via Zabarella, 34, 35100 Padova PD", "lat": 45.4025, "lon": 11.8885},
  {"indirizzo abitazione": "Via Umberto I, 67, 35100 Padova PD", "lat": 45.4095, "lon": 11.8695},
  {"indirizzo abitazione": "Via Dante, 89, 35100 Padova PD", "lat": 45.4035, "lon": 11.8825},
  {"indirizzo abitazione": "Via Venezia, 123, 35100 Padova PD", "lat": 45.4105, "lon": 11.8665},
  {"indirizzo abitazione": "Via Trieste, 156, 35100 Padova PD", "lat": 45.4015, "lon": 11.8875},
  {"indirizzo abitazione": "Via Garibaldi, 78, 35100 Padova PD", "lat": 45.4115, "lon": 11.8635},
  {"indirizzo abitazione": "Via Cavour, 234, 35100 Padova PD", "lat": 45.4005, "lon": 11.8895},
  {"indirizzo abitazione": "Via Verdi, 345, 35100 Padova PD", "lat": 45.4125, "lon": 11.8615},
  {"indirizzo abitazione": "Via Manzoni, 45, 35100 Padova PD", "lat": 45.3995, "lon": 11.8915},
  {"indirizzo abitazione": "Via Foscolo, 67, 35100 Padova PD", "lat": 45.4135, "lon": 11.8595},
  {"indirizzo abitazione": "Via Carducci, 89, 35100 Padova PD", "lat": 45.3985, "lon": 11.8935},
  {"indirizzo abitazione": "Via Leopardi, 123, 35100 Padova PD", "lat": 45.4145, "lon": 11.8575},
  {"indirizzo abitazione": "Via Pascoli, 156, 35100 Padova PD", "lat": 45.3975, "lon": 11.8955},
  {"indirizzo abitazione": "Via D'Annunzio, 234, 35100 Padova PD", "lat": 45.4155, "lon": 11.8555},
  {"indirizzo abitazione": "Via Pellico, 345, 35100 Padova PD", "lat": 45.3965, "lon": 11.8975},
  {"indirizzo abitazione": "Via Gioberti, 45, 35100 Padova PD", "lat": 45.4165, "lon": 11.8535},
  {"indirizzo abitazione": "Via Cairoli, 67, 35100 Padova PD", "lat": 45.3955, "lon": 11.8995},
  {"indirizzo abitazione": "Via Mameli, 89, 35100 Padova PD", "lat": 45.4175, "lon": 11.8515},
  {"indirizzo abitazione": "Via Petrarca, 123, 35100 Padova PD", "lat": 45.3945, "lon": 11.9015},
  {"indirizzo abitazione": "Via Tasso, 156, 35100 Padova PD", "lat": 45.4185, "lon": 11.8495},
  {"indirizzo abitazione": "Via Ariosto, 234, 35100 Padova PD", "lat": 45.3935, "lon": 11.9035},
  {"indirizzo abitazione": "Via Goldoni, 345, 35100 Padova PD", "lat": 45.4195, "lon": 11.8475},
  {"indirizzo abitazione": "Via Alfieri, 45, 35100 Padova PD", "lat": 45.3925, "lon": 11.9055},
  {"indirizzo abitazione": "Via Metastasio, 67, 35100 Padova PD", "lat": 45.4205, "lon": 11.8455},
  {"indirizzo abitazione": "Via Bembo, 89, 35100 Padova PD", "lat": 45.3915, "lon": 11.9075},
  {"indirizzo abitazione": "Via Sarpi, 123, 35100 Padova PD", "lat": 45.4215, "lon": 11.8435},
  {"indirizzo abitazione": "Via Falier, 156, 35100 Padova PD", "lat": 45.3905, "lon": 11.9095},
  {"indirizzo abitazione": "Via Tiepolo, 234, 35100 Padova PD", "lat": 45.4225, "lon": 11.8415},
  {"indirizzo abitazione": "Via Veronese, 345, 35100 Padova PD", "lat": 45.3895, "lon": 11.9115},
  {"indirizzo abitazione": "Via Tintoretto, 45, 35100 Padova PD", "lat": 45.4235, "lon": 11.8395},
  {"indirizzo abitazione": "Via Bellini, 67, 35100 Padova PD", "lat": 45.3885, "lon": 11.9135},
  {"indirizzo abitazione": "Via Donizetti, 89, 35100 Padova PD", "lat": 45.4245, "lon": 11.8375},
  {"indirizzo abitazione": "Via Rossini, 123, 35100 Padova PD", "lat": 45.3875, "lon": 11.9155},
  {"indirizzo abitazione": "Via Puccini, 156, 35100 Padova PD", "lat": 45.4255, "lon": 11.8355},
  {"indirizzo abitazione": "Via Vivaldi, 234, 35100 Padova PD", "lat": 45.3865, "lon": 11.9175},
  {"indirizzo abitazione": "Via Monteverdi, 345, 35100 Padova PD", "lat": 45.4265, "lon": 11.8335},
  {"indirizzo abitazione": "Via Palestrina, 45, 35100 Padova PD", "lat": 45.3855, "lon": 11.9195},
  {"indirizzo abitazione": "Via Scarlatti, 67, 35100 Padova PD", "lat": 45.4275, "lon": 11.8315},
  {"indirizzo abitazione": "Via Albinoni, 89, 35100 Padova PD", "lat": 45.3845, "lon": 11.9215},
  {"indirizzo abitazione": "Via Corelli, 123, 35100 Padova PD", "lat": 45.4285, "lon": 11.8295},
  {"indirizzo abitazione": "Via Tartini, 156, 35100 Padova PD", "lat": 45.3835, "lon": 11.9235},
  {"indirizzo abitazione": "Via Marcello, 234, 35100 Padova PD", "lat": 45.4295, "lon": 11.8275},
  {"indirizzo abitazione": "Via Galuppi, 345, 35100 Padova PD", "lat": 45.3825, "lon": 11.9255},
  {"indirizzo abitazione": "Via Sammartini, 45, 35100 Padova PD", "lat": 45.4305, "lon": 11.8255},
  {"indirizzo abitazione": "Via Boccherini, 67, 35100 Padova PD", "lat": 45.3815, "lon": 11.9275},
  {"indirizzo abitazione": "Via Clementi, 89, 35100 Padova PD", "lat": 45.4315, "lon": 11.8235},
  {"indirizzo abitazione": "Via Cherubini, 123, 35100 Padova PD", "lat": 45.3805, "lon": 11.9295},
  {"indirizzo abitazione": "Via Spontini, 156, 35100 Padova PD", "lat": 45.4325, "lon": 11.8215},
  {"indirizzo abitazione": "Via Paisiello, 234, 35100 Padova PD", "lat": 45.3795, "lon": 11.9315},
  {"indirizzo abitazione": "Via Cimarosa, 345, 35100 Padova PD", "lat": 45.4335, "lon": 11.8195},
  {"indirizzo abitazione": "Via Salieri, 45, 35100 Padova PD", "lat": 45.3785, "lon": 11.9335},
  {"indirizzo abitazione": "Via Lotti, 67, 35100 Padova PD", "lat": 45.4345, "lon": 11.8175},
  {"indirizzo abitazione": "Via Stradella, 89, 35100 Padova PD", "lat": 45.3775, "lon": 11.9355},
  {"indirizzo abitazione": "Via Pergolesi, 123, 35100 Padova PD", "lat": 45.4355, "lon": 11.8155},
  {"indirizzo abitazione": "Via Piccinni, 156, 35100 Padova PD", "lat": 45.3765, "lon": 11.9375},
  {"indirizzo abitazione": "Via Sacchini, 234, 35100 Padova PD", "lat": 45.4365, "lon": 11.8135},
  {"indirizzo abitazione": "Via Traetta, 345, 35100 Padova PD", "lat": 45.3755, "lon": 11.9395},
  {"indirizzo abitazione": "Via Roma, 12, 35031 Abano Terme PD", "lat": 45.3597, "lon": 11.7897},
  {"indirizzo abitazione": "Via Nazionale, 34, 35031 Abano Terme PD", "lat": 45.3585, "lon": 11.7915},
  {"indirizzo abitazione": "Via Monteortone, 56, 35031 Abano Terme PD", "lat": 45.3612, "lon": 11.7875},
  {"indirizzo abitazione": "Via Appia Monterosso, 78, 35031 Abano Terme PD", "lat": 45.3575, "lon": 11.7932},
  {"indirizzo abitazione": "Via Pietro d'Abano, 123, 35031 Abano Terme PD", "lat": 45.3625, "lon": 11.7855},
  {"indirizzo abitazione": "Via Flacco, 145, 35031 Abano Terme PD", "lat": 45.3565, "lon": 11.7948},
  {"indirizzo abitazione": "Via Valerio Flacco, 167, 35031 Abano Terme PD", "lat": 45.3635, "lon": 11.7838},
  {"indirizzo abitazione": "Via Astichello, 189, 35031 Abano Terme PD", "lat": 45.3555, "lon": 11.7965},
  {"indirizzo abitazione": "Via Montirone, 234, 35031 Abano Terme PD", "lat": 45.3645, "lon": 11.7818},
  {"indirizzo abitazione": "Via Busonera, 256, 35031 Abano Terme PD", "lat": 45.3545, "lon": 11.7982},
  {"indirizzo abitazione": "Via Roma, 12, 35036 Montegrotto Terme PD", "lat": 45.3297, "lon": 11.7897},
  {"indirizzo abitazione": "Via Nazionale, 34, 35036 Montegrotto Terme PD", "lat": 45.3285, "lon": 11.7915},
  {"indirizzo abitazione": "Via Aureliana, 56, 35036 Montegrotto Terme PD", "lat": 45.3312, "lon": 11.7875},
  {"indirizzo abitazione": "Via Castello, 78, 35036 Montegrotto Terme PD", "lat": 45.3275, "lon": 11.7932},
  {"indirizzo abitazione": "Via Colli Euganei, 123, 35036 Montegrotto Terme PD", "lat": 45.3325, "lon": 11.7855},
  {"indirizzo abitazione": "Via Roma, 12, 35013 Cittadella PD", "lat": 45.6497, "lon": 11.7897},
  {"indirizzo abitazione": "Via Nazionale, 34, 35013 Cittadella PD", "lat": 45.6485, "lon": 11.7915},
  {"indirizzo abitazione": "Via Borgo Bassano, 56, 35013 Cittadella PD", "lat": 45.6512, "lon": 11.7875},
  {"indirizzo abitazione": "Via Borgo Treviso, 78, 35013 Cittadella PD", "lat": 45.6475, "lon": 11.7932},
  {"indirizzo abitazione": "Via Borgo Vicenza, 123, 35013 Cittadella PD", "lat": 45.6525, "lon": 11.7855},
  {"indirizzo abitazione": "Via Borgo Padova, 145, 35013 Cittadella PD", "lat": 45.6465, "lon": 11.7948},
  {"indirizzo abitazione": "Via Borgo Murello, 167, 35013 Cittadella PD", "lat": 45.6535, "lon": 11.7838},
  {"indirizzo abitazione": "Via Roma, 12, 35012 Camposampiero PD", "lat": 45.5697, "lon": 11.9297},
  {"indirizzo abitazione": "Via Nazionale, 34, 35012 Camposampiero PD", "lat": 45.5685, "lon": 11.9315},
  {"indirizzo abitazione": "Via Tiso, 56, 35012 Camposampiero PD", "lat": 45.5712, "lon": 11.9275},
  {"indirizzo abitazione": "Via San Martino, 78, 35012 Camposampiero PD", "lat": 45.5675, "lon": 11.9332},
  {"indirizzo abitazione": "Via Pilastrello, 123, 35012 Camposampiero PD", "lat": 45.5725, "lon": 11.9255},
  {"indirizzo abitazione": "Via Roma, 12, 35042 Este PD", "lat": 45.2297, "lon": 11.6581},
  {"indirizzo abitazione": "Via Nazionale, 34, 35042 Este PD", "lat": 45.2285, "lon": 11.6599},
  {"indirizzo abitazione": "Via Stazie Bragane, 56, 35042 Este PD", "lat": 45.2312, "lon": 11.6558},
  {"indirizzo abitazione": "Via Alberi, 78, 35042 Este PD", "lat": 45.2275, "lon": 11.6615},
  {"indirizzo abitazione": "Via Principe Umberto, 123, 35042 Este PD", "lat": 45.2325, "lon": 11.6538},
  {"indirizzo abitazione": "Via Roma, 12, 35020 Vigodarzere PD", "lat": 45.4597, "lon": 11.8597},
  {"indirizzo abitazione": "Via Nazionale, 34, 35020 Vigodarzere PD", "lat": 45.4585, "lon": 11.8615},
  {"indirizzo abitazione": "Via Volturno, 56, 35020 Vigodarzere PD", "lat": 45.4612, "lon": 11.8575},
  {"indirizzo abitazione": "Via Piave, 78, 35020 Vigodarzere PD", "lat": 45.4575, "lon": 11.8632},
  {"indirizzo abitazione": "Via Roma, 12, 35020 Albignasego PD", "lat": 45.3297, "lon": 11.8897},
  {"indirizzo abitazione": "Via Nazionale, 34, 35020 Albignasego PD", "lat": 45.3285, "lon": 11.8915},
  {"indirizzo abitazione": "Via Lion, 56, 35020 Albignasego PD", "lat": 45.3312, "lon": 11.8875},
  {"indirizzo abitazione": "Via San Giacomo, 78, 35020 Albignasego PD", "lat": 45.3275, "lon": 11.8932},
  {"indirizzo abitazione": "Via Roma, 12, 35018 San Martino di Lupari PD", "lat": 45.6697, "lon": 11.8497},
  {"indirizzo abitazione": "Via Roma, 12, 35010 Cadoneghe PD", "lat": 45.4397, "lon": 11.9297},
  {"indirizzo abitazione": "Via Roma, 12, 35014 Fontaniva PD", "lat": 45.6372, "lon": 11.7556},
  {"indirizzo abitazione": "Via Roma, 12, 35015 Galliera Veneta PD", "lat": 45.6597, "lon": 11.8297},
  {"indirizzo abitazione": "Via Roma, 12, 35017 Piombino Dese PD", "lat": 45.5897, "lon": 11.9897},
  {"indirizzo abitazione": "Via Roma, 12, 35019 Tombolo PD", "lat": 45.6397, "lon": 11.7997},
  {"indirizzo abitazione": "Via Roma, 12, 35022 Cartura PD", "lat": 45.2897, "lon": 11.8797},
  {"indirizzo abitazione": "Via Roma, 12, 35023 Bagnoli di Sopra PD", "lat": 45.1697, "lon": 11.8797},
  {"indirizzo abitazione": "Via Roma, 12, 35024 Bovolenta PD", "lat": 45.2597, "lon": 11.9597},
  {"indirizzo abitazione": "Via Roma, 12, 35025 Brugine PD", "lat": 45.2997, "lon": 11.9797},
  {"indirizzo abitazione": "Via Roma, 12, 35026 Conselve PD", "lat": 45.2397, "lon": 12.0197},
  {"indirizzo abitazione": "Via Roma, 12, 35027 Noventa Padovana PD", "lat": 45.3997, "lon": 11.9497},
  {"indirizzo abitazione": "Via Roma, 12, 35028 Piove di Sacco PD", "lat": 45.2997, "lon": 12.0397},
  {"indirizzo abitazione": "Via Roma, 12, 35029 Pontelongo PD", "lat": 45.2197, "lon": 11.9997},
  {"indirizzo abitazione": "Via Roma, 12, 35030 Rubano PD", "lat": 45.4197, "lon": 11.8097},
  {"indirizzo abitazione": "Via Roma, 12, 35032 Arquà Petrarca PD", "lat": 45.2697, "lon": 11.7197},
  {"indirizzo abitazione": "Via Roma, 12, 35033 Bressanvido PD", "lat": 45.6097, "lon": 11.6897},
  {"indirizzo abitazione": "Via Roma, 12, 35034 Lozzo Atestino PD", "lat": 45.2897, "lon": 11.6397},
  {"indirizzo abitazione": "Via Roma, 12, 35035 Mestrino PD", "lat": 45.4597, "lon": 11.7697},
  {"indirizzo abitazione": "Via Roma, 12, 35037 Teolo PD", "lat": 45.3597, "lon": 11.6797},
  {"indirizzo abitazione": "Via Roma, 12, 35038 Torreglia PD", "lat": 45.3797, "lon": 11.7097},
  {"indirizzo abitazione": "Via Roma, 12, 35039 Villa del Conte PD", "lat": 45.6197, "lon": 11.8697},
  {"indirizzo abitazione": "Via Roma, 12, 35040 Casale di Scodosia PD", "lat": 45.1897, "lon": 11.4897},
  {"indirizzo abitazione": "Via Roma, 12, 35041 Battaglia Terme PD", "lat": 45.2897, "lon": 11.7797},
  {"indirizzo abitazione": "Via Roma, 12, 35043 Monselice PD", "lat": 45.2397, "lon": 11.7497},
  {"indirizzo abitazione": "Via Roma, 12, 35044 Montagnana PD", "lat": 45.2297, "lon": 11.4697},
  {"indirizzo abitazione": "Via Roma, 12, 35045 Ospedaletto Euganeo PD", "lat": 45.2197, "lon": 11.6097},
  {"scuola": "Università degli Studi di Padova, Via 8 Febbraio, 35100 Padova PD", "lat": 45.4070, "lon": 11.8770},
  {"scuola": "Liceo Scientifico Cornaro, Via Riccoboni, 35100 Padova PD", "lat": 45.4060, "lon": 11.8750},
  {"scuola": "Liceo Classico Tito Livio, Riviera Tito Livio, 35100 Padova PD", "lat": 45.4085, "lon": 11.8805},
  {"scuola": "Liceo Scientifico Curiel, Via Duca d'Aosta, 35100 Padova PD", "lat": 45.4045, "lon": 11.8825},
  {"scuola": "IIS Alberti, Via Piovego, 35100 Padova PD", "lat": 45.4125, "lon": 11.8685},
  {"scuola": "IIS Bernardi, Via Volturno, 35100 Padova PD", "lat": 45.4105, "lon": 11.8705},
  {"scuola": "IIS Duca d'Aosta, Via Concordia, 35100 Padova PD", "lat": 45.4015, "lon": 11.8885},
  {"scuola": "Istituto Tecnico Scalcerle, Via Scalcerle, 35100 Padova PD", "lat": 45.3985, "lon": 11.8915},
  {"scuola": "Istituto Professionale Marcopolo, Via Sette Martiri, 35100 Padova PD", "lat": 45.4195, "lon": 11.8515},
  {"scuola": "Liceo Artistico Modigliani, Via Vescovado, 35100 Padova PD", "lat": 45.4055, "lon": 11.8795},
  {"scuola": "Conservatorio Pollini, Via Eremitani, 35100 Padova PD", "lat": 45.4075, "lon": 11.8775},
  {"scuola": "Istituto Comprensivo Briosco, Via Briosco, 35100 Padova PD", "lat": 45.4135, "lon": 11.8655},
  {"scuola": "Scuola Primaria Arcobaleno, Via Antenore, 35100 Padova PD", "lat": 45.4025, "lon": 11.8845},
  {"scuola": "Scuola Secondaria Galilei, Via Galilei, 35100 Padova PD", "lat": 45.4095, "lon": 11.8715},
  {"scuola": "Scuola dell'Infanzia Rodari, Via Volturno, 35100 Padova PD", "lat": 45.4115, "lon": 11.8695},
  {"scuola": "Istituto Comprensivo Abano, Via Roma, 45, 35031 Abano Terme PD", "lat": 45.3592, "lon": 11.7905},
  {"scuola": "Scuola Primaria Abano, Via Nazionale, 67, 35031 Abano Terme PD", "lat": 45.3605, "lon": 11.7885},
  {"scuola": "Istituto Comprensivo Montegrotto, Via Roma, 45, 35036 Montegrotto Terme PD", "lat": 45.3292, "lon": 11.7905},
  {"scuola": "Istituto Comprensivo Cittadella, Via Roma, 45, 35013 Cittadella PD", "lat": 45.6492, "lon": 11.7905},
  {"scuola": "Liceo Tron Cittadella, Via Borgo Bassano, 23, 35013 Cittadella PD", "lat": 45.6505, "lon": 11.7885},
  {"scuola": "Istituto Comprensivo Camposampiero, Via Roma, 45, 35012 Camposampiero PD", "lat": 45.5692, "lon": 11.9305},
  {"scuola": "Istituto Comprensivo Este, Via Roma, 45, 35042 Este PD", "lat": 45.2292, "lon": 11.6590},
  {"scuola": "Liceo Bocchi Este, Via Nazionale, 67, 35042 Este PD", "lat": 45.2305, "lon": 11.6570},
  {"scuola": "Istituto Comprensivo Vigodarzere, Via Roma, 45, 35020 Vigodarzere PD", "lat": 45.4592, "lon": 11.8605},
  {"scuola": "Istituto Comprensivo Albignasego, Via Roma, 45, 35020 Albignasego PD", "lat": 45.3292, "lon": 11.8905},
  {"scuola": "Istituto Comprensivo San Martino, Via Roma, 45, 35018 San Martino di Lupari PD", "lat": 45.6692, "lon": 11.8505},
  {"scuola": "Istituto Comprensivo Cadoneghe, Via Roma, 45, 35010 Cadoneghe PD", "lat": 45.4392, "lon": 11.9305},
  {"scuola": "Istituto Comprensivo Fontaniva, Via Roma, 45, 35014 Fontaniva PD", "lat": 45.6367, "lon": 11.7565},
  {"scuola": "Istituto Comprensivo Galliera, Via Roma, 45, 35015 Galliera Veneta PD", "lat": 45.6592, "lon": 11.8305},
  {"scuola": "Istituto Comprensivo Piombino, Via Roma, 45, 35017 Piombino Dese PD", "lat": 45.5892, "lon": 11.9905},
  {"scuola": "Istituto Comprensivo Noventa, Via Roma, 45, 35027 Noventa Padovana PD", "lat": 45.3992, "lon": 11.9505},
  {"scuola": "Istituto Comprensivo Piove, Via Roma, 45, 35028 Piove di Sacco PD", "lat": 45.2992, "lon": 12.0405},
  {"scuola": "Istituto Comprensivo Rubano, Via Roma, 45, 35030 Rubano PD", "lat": 45.4192, "lon": 11.8105},
  {"scuola": "Istituto Comprensivo Monselice, Via Roma, 45, 35043 Monselice PD", "lat": 45.2392, "lon": 11.7505},
  {"scuola": "Istituto Comprensivo Montagnana, Via Roma, 45, 35044 Montagnana PD", "lat": 45.2292, "lon": 11.4705},
  {"impianto sportivo": "Stadio Euganeo, Corso Australia, 35100 Padova PD", "lat": 45.3852, "lon": 11.9055},
  {"impianto sportivo": "Palazzetto dello Sport, Via San Marco, 35100 Padova PD", "lat": 45.4165, "lon": 11.8695},
  {"impianto sportivo": "Piscina Comunale, Via Rismondo, 35100 Padova PD", "lat": 45.4235, "lon": 11.8415},
  {"impianto sportivo": "Tennis Club Padova, Via Facciolati, 35100 Padova PD", "lat": 45.4125, "lon": 11.8585},
  {"impianto sportivo": "Centro Sportivo Plebiscito, Via del Plebiscito, 35100 Padova PD", "lat": 45.3985, "lon": 11.8925},
  {"impianto sportivo": "Stadio del Baseball, Via Cave, 35100 Padova PD", "lat": 45.4275, "lon": 11.8325},
  {"impianto sportivo": "Campo Sportivo Abano, Via Roma, 123, 35031 Abano Terme PD", "lat": 45.3615, "lon": 11.7875},
  {"impianto sportivo": "Piscina Termale Abano, Via Nazionale, 156, 35031 Abano Terme PD", "lat": 45.3582, "lon": 11.7918},
  {"impianto sportivo": "Centro Sportivo Montegrotto, Via Roma, 123, 35036 Montegrotto Terme PD", "lat": 45.3295, "lon": 11.7885},
  {"impianto sportivo": "Stadio Cittadella, Via Roma, 156, 35013 Cittadella PD", "lat": 45.6485, "lon": 11.7925},
  {"impianto sportivo": "Palestra Camposampiero, Via Roma, 123, 35012 Camposampiero PD", "lat": 45.5695, "lon": 11.9285},
  {"impianto sportivo": "Campo Sportivo Este, Via Roma, 123, 35042 Este PD", "lat": 45.2285, "lon": 11.6605},
  {"impianto sportivo": "Centro Sportivo Vigodarzere, Via Roma, 123, 35020 Vigodarzere PD", "lat": 45.4585, "lon": 11.8625},
  {"impianto sportivo": "Campo Sportivo Albignasego, Via Roma, 123, 35020 Albignasego PD", "lat": 45.3285, "lon": 11.8925},
  {"impianto sportivo": "Palestra San Martino, Via Roma, 123, 35018 San Martino di Lupari PD", "lat": 45.6685, "lon": 11.8515},
  {"impianto sportivo": "Centro Sportivo Cadoneghe, Via Roma, 123, 35010 Cadoneghe PD", "lat": 45.4385, "lon": 11.9315},
  {"impianto sportivo": "Campo Sportivo Noventa, Via Roma, 123, 35027 Noventa Padovana PD", "lat": 45.3985, "lon": 11.9515},
  {"impianto sportivo": "Centro Sportivo Piove, Via Roma, 123, 35028 Piove di Sacco PD", "lat": 45.2985, "lon": 12.0415},
  {"impianto sportivo": "Palestra Rubano, Via Roma, 123, 35030 Rubano PD", "lat": 45.4185, "lon": 11.8115},
  {"impianto sportivo": "Campo Sportivo Monselice, Via Roma, 123, 35043 Monselice PD", "lat": 45.2385, "lon": 11.7515},
  {"impianto sportivo": "Centro Sportivo Montagnana, Via Roma, 123, 35044 Montagnana PD", "lat": 45.2285, "lon": 11.4715},
  {"impianto lavorativo": "Zona Industriale Nord, Via dell'Industria, 35100 Padova PD", "lat": 45.3900, "lon": 11.8900},
  {"impianto lavorativo": "Centro Commerciale Giotto, Via Zabarella, 35100 Padova PD", "lat": 45.4100, "lon": 11.8650},
  {"impianto lavorativo": "Zona Industriale Sud, Via Rismondo, 234, 35100 Padova PD", "lat": 45.4245, "lon": 11.8385},
  {"impianto lavorativo": "Centro Commerciale Esp, Via Galeno, 35100 Padova PD", "lat": 45.3855, "lon": 11.9185},
  {"impianto lavorativo": "Polo Tecnologico Torre Archimede, Via Gradenigo, 35100 Padova PD", "lat": 45.4105, "lon": 11.8715},
  {"impianto lavorativo": "Centro Direzionale, Via Venezia, 234, 35100 Padova PD", "lat": 45.4115, "lon": 11.8645},
  {"impianto lavorativo": "Distretto Biomedicale, Via Gradenigo, 345, 35100 Padova PD", "lat": 45.4095, "lon": 11.8735},
  {"impianto lavorativo": "Zona Artigianale ZIP, Via Cave, 156, 35100 Padova PD", "lat": 45.4285, "lon": 11.8285},
  {"impianto lavorativo": "Centro Commerciale Abano, Via Roma, 156, 35031 Abano Terme PD", "lat": 45.3575, "lon": 11.7935},
  {"impianto lavorativo": "Polo Termale Montegrotto, Via Roma, 156, 35036 Montegrotto Terme PD", "lat": 45.3275, "lon": 11.7935},
  {"impianto lavorativo": "Zona Industriale Cittadella, Via Roma, 189, 35013 Cittadella PD", "lat": 45.6475, "lon": 11.7945},
  {"impianto lavorativo": "Centro Commerciale Camposampiero, Via Roma, 156, 35012 Camposampiero PD", "lat": 45.5675, "lon": 11.9335},
  {"impianto lavorativo": "Zona Artigianale Este, Via Roma, 156, 35042 Este PD", "lat": 45.2275, "lon": 11.6625},
  {"impianto lavorativo": "Centro Commerciale Vigodarzere, Via Roma, 156, 35020 Vigodarzere PD", "lat": 45.4575, "lon": 11.8645},
  {"impianto lavorativo": "Polo Logistico Albignasego, Via Roma, 156, 35020 Albignasego PD", "lat": 45.3275, "lon": 11.8945},
  {"impianto lavorativo": "Zona Industriale San Martino, Via Roma, 156, 35018 San Martino di Lupari PD", "lat": 45.6675, "lon": 11.8535},
  {"impianto lavorativo": "Centro Commerciale Cadoneghe, Via Roma, 156, 35010 Cadoneghe PD", "lat": 45.4375, "lon": 11.9335},
  {"impianto lavorativo": "Polo Tecnologico Noventa, Via Roma, 156, 35027 Noventa Padovana PD", "lat": 45.3975, "lon": 11.9535},
  {"impianto lavorativo": "Zona Artigianale Piove, Via Roma, 156, 35028 Piove di Sacco PD", "lat": 45.2975, "lon": 12.0435},
  {"impianto lavorativo": "Centro Direzionale Rubano, Via Roma, 156, 35030 Rubano PD", "lat": 45.4175, "lon": 11.8135},
  {"impianto lavorativo": "Polo Industriale Monselice, Via Roma, 156, 35043 Monselice PD", "lat": 45.2375, "lon": 11.7535},
  {"impianto lavorativo": "Zona Artigianale Montagnana, Via Roma, 156, 35044 Montagnana PD", "lat": 45.2275, "lon": 11.4735},
  {"rsa": "Casa di Riposo Oic, Via Ospedale Civile, 35100 Padova PD", "lat": 45.4058, "lon": 11.8782},
  {"rsa": "RSA Sant'Antonio, Via San Massimo, 35100 Padova PD", "lat": 45.4138, "lon": 11.8662},
  {"rsa": "Casa di Cura Abano, Via Pietro d'Abano, 189, 35031 Abano Terme PD", "lat": 45.3635, "lon": 11.7845},
  {"rsa": "RSA Villa Salus, Via Nazionale, 234, 35031 Abano Terme PD", "lat": 45.3565, "lon": 11.7955},
  {"rsa": "Casa di Riposo Montegrotto, Via Aureliana, 123, 35036 Montegrotto Terme PD", "lat": 45.3315, "lon": 11.7865},
  {"rsa": "RSA Cittadella, Via Borgo Bassano, 189, 35013 Cittadella PD", "lat": 45.6515, "lon": 11.7865},
  {"rsa": "Casa di Riposo Camposampiero, Via Tiso, 123, 35012 Camposampiero PD", "lat": 45.5715, "lon": 11.9265},
  {"rsa": "RSA Este, Via Principe Umberto, 189, 35042 Este PD", "lat": 45.2335, "lon": 11.6525},
  {"rsa": "Casa di Riposo Vigodarzere, Via Volturno, 123, 35020 Vigodarzere PD", "lat": 45.4615, "lon": 11.8565},
  {"rsa": "RSA Albignasego, Via Lion, 123, 35020 Albignasego PD", "lat": 45.3315, "lon": 11.8865},
  {"rsa": "Casa di Riposo San Martino, Via Roma, 189, 35018 San Martino di Lupari PD", "lat": 45.6715, "lon": 11.8485},
  {"rsa": "RSA Cadoneghe, Via Roma, 189, 35010 Cadoneghe PD", "lat": 45.4415, "lon": 11.9285},
  {"rsa": "Casa di Riposo Noventa, Via Roma, 189, 35027 Noventa Padovana PD", "lat": 45.4015, "lon": 11.9485},
  {"rsa": "RSA Piove di Sacco, Via Roma, 189, 35028 Piove di Sacco PD", "lat": 45.3015, "lon": 12.0385},
  {"rsa": "Casa di Riposo Rubano, Via Roma, 189, 35030 Rubano PD", "lat": 45.4215, "lon": 11.8085},
  {"rsa": "RSA Monselice, Via Roma, 189, 35043 Monselice PD", "lat": 45.2415, "lon": 11.7485},
  {"rsa": "Casa di Riposo Montagnana, Via Roma, 189, 35044 Montagnana PD", "lat": 45.2315, "lon": 11.4685},
  {"strada": "A4 Autostrada Serenissima, km 420, 35100 Padova PD", "lat": 45.4200, "lon": 11.8500},
  {"strada": "SS 16 Adriatica, km 180, 35100 Padova PD", "lat": 45.3950, "lon": 11.9100},
  {"strada": "A57 Tangenziale di Padova, km 12, 35100 Padova PD", "lat": 45.4350, "lon": 11.8150},
  {"strada": "SS 47 della Valsugana, km 45, 35100 Padova PD", "lat": 45.4450, "lon": 11.7850},
  {"strada": "SS 515 Noalese, km 23, 35100 Padova PD", "lat": 45.4550, "lon": 11.7550},
  {"strada": "A13 Autostrada Bologna-Padova, km 125, 35100 Padova PD", "lat": 45.3750, "lon": 11.9350},
  {"strada": "SP 1 Termo-Euganea, km 15, 35031 Abano Terme PD", "lat": 45.3450, "lon": 11.8150},
  {"strada": "SS 250 Castellana, km 34, 35036 Montegrotto Terme PD", "lat": 45.3150, "lon": 11.8350},
  {"strada": "A4 Autostrada Serenissima, km 445, 35013 Cittadella PD", "lat": 45.6650, "lon": 11.7650},
  {"strada": "SP 2 di Camposampiero, km 18, 35012 Camposampiero PD", "lat": 45.5850, "lon": 11.9150},
  {"strada": "A13 Autostrada Bologna-Padova, km 145, 35042 Este PD", "lat": 45.2150, "lon": 11.6850},
  {"strada": "SS 515 Noalese, km 8, 35020 Vigodarzere PD", "lat": 45.4750, "lon": 11.8350},
  {"strada": "A57 Tangenziale di Padova, km 18, 35020 Albignasego PD", "lat": 45.3150, "lon": 11.9150},
  {"strada": "SP 3 del Brenta, km 25, 35018 San Martino di Lupari PD", "lat": 45.6850, "lon": 11.8250},
  {"strada": "SS 515 Noalese, km 15, 35010 Cadoneghe PD", "lat": 45.4550, "lon": 11.9550},
  {"strada": "A57 Tangenziale di Padova, km 8, 35027 Noventa Padovana PD", "lat": 45.4150, "lon": 11.9250},
  {"strada": "A13 Autostrada Bologna-Padova, km 155, 35028 Piove di Sacco PD", "lat": 45.2850, "lon": 12.0650},
  {"strada": "A57 Tangenziale di Padova, km 5, 35030 Rubano PD", "lat": 45.4350, "lon": 11.7950},
  {"strada": "A13 Autostrada Bologna-Padova, km 165, 35043 Monselice PD", "lat": 45.2250, "lon": 11.7750},
  {"strada": "A13 Autostrada Bologna-Padova, km 175, 35044 Montagnana PD", "lat": 45.2050, "lon": 11.4950},
  {"strada": "SP 4 del Colli Euganei, km 12, 35032 Arquà Petrarca PD", "lat": 45.2850, "lon": 11.6950},
  {"strada": "SP 5 Battaglia-Galzignano, km 8, 35041 Battaglia Terme PD", "lat": 45.3050, "lon": 11.7650},
  {"strada": "SS 10 Padana Inferiore, km 234, 35023 Bagnoli di Sopra PD", "lat": 45.1850, "lon": 11.8550},
  {"strada": "SP 6 di Bovolenta, km 15, 35024 Bovolenta PD", "lat": 45.2750, "lon": 11.9350},
  {"strada": "SP 7 di Brugine, km 18, 35025 Brugine PD", "lat": 45.3150, "lon": 11.9550},
  {"strada": "A13 Autostrada Bologna-Padova, km 168, 35026 Conselve PD", "lat": 45.2550, "lon": 12.0050},
  {"strada": "SP 8 di Pontelongo, km 12, 35029 Pontelongo PD", "lat": 45.2350, "lon": 11.9850},
  {"strada": "SP 9 di Teolo, km 15, 35037 Teolo PD", "lat": 45.3750, "lon": 11.6550},
  {"strada": "SP 10 di Torreglia, km 18, 35038 Torreglia PD", "lat": 45.3950, "lon": 11.6950},
  {"strada": "SP 11 di Villa del Conte, km 22, 35039 Villa del Conte PD", "lat": 45.6350, "lon": 11.8550},
  {"strada": "SS 10 Padana Inferiore, km 254, 35040 Casale di Scodosia PD", "lat": 45.2050, "lon": 11.4650},
  {"strada": "SP 12 di Ospedaletto, km 8, 35045 Ospedaletto Euganeo PD", "lat": 45.2350, "lon": 11.5850},
  {"indirizzo abitazione": "Via Battisti, 234, 35121 Padova PD", "lat": 45.41150, "lon": 11.87850},
  {"indirizzo abitazione": "Via Manzoni, 345, 35121 Padova PD", "lat": 45.40250, "lon": 11.88750},
  {"indirizzo abitazione": "Via Leopardi, 67, 35121 Padova PD", "lat": 45.41250, "lon": 11.87750},
  {"indirizzo abitazione": "Via Pascoli, 89, 35121 Padova PD", "lat": 45.40150, "lon": 11.88850},
  {"indirizzo abitazione": "Via D'Annunzio, 123, 35121 Padova PD", "lat": 45.41350, "lon": 11.87650},
  {"indirizzo abitazione": "Via Carducci, 156, 35121 Padova PD", "lat": 45.40050, "lon": 11.88950},
  {"indirizzo abitazione": "Via Pirandello, 234, 35121 Padova PD", "lat": 45.41450, "lon": 11.87550},
  {"indirizzo abitazione": "Via Ungaretti, 345, 35121 Padova PD", "lat": 45.39950, "lon": 11.89050},
  {"indirizzo abitazione": "Via Montale, 67, 35121 Padova PD", "lat": 45.41550, "lon": 11.87450},
  {"indirizzo abitazione": "Via Quasimodo, 89, 35121 Padova PD", "lat": 45.39850, "lon": 11.89150},
  {"indirizzo abitazione": "Via Saba, 123, 35121 Padova PD", "lat": 45.41650, "lon": 11.87350},
  {"indirizzo abitazione": "Via Pavese, 156, 35121 Padova PD", "lat": 45.39750, "lon": 11.89250},
  {"indirizzo abitazione": "Via Calvino, 234, 35121 Padova PD", "lat": 45.41750, "lon": 11.87250},
  {"indirizzo abitazione": "Via Moravia, 345, 35121 Padova PD", "lat": 45.39650, "lon": 11.89350},
  {"indirizzo abitazione": "Via Sciascia, 67, 35121 Padova PD", "lat": 45.41850, "lon": 11.87150},
  {"indirizzo abitazione": "Via Eco, 89, 35121 Padova PD", "lat": 45.39550, "lon": 11.89450},
  {"indirizzo abitazione": "Via Primo Levi, 123, 35121 Padova PD", "lat": 45.41950, "lon": 11.87050},
  {"indirizzo abitazione": "Via Fenoglio, 156, 35121 Padova PD", "lat": 45.39450, "lon": 11.89550},
  {"indirizzo abitazione": "Via Pasolini, 234, 35121 Padova PD", "lat": 45.42050, "lon": 11.86950},
  {"indirizzo abitazione": "Via Soldati, 345, 35121 Padova PD", "lat": 45.39350, "lon": 11.89650},
  {"indirizzo abitazione": "Via Viale, 67, 35036 Montegrotto Terme PD", "lat": 45.32500, "lon": 11.78500},
  {"indirizzo abitazione": "Via delle Rose, 89, 35036 Montegrotto Terme PD", "lat": 45.32400, "lon": 11.78600},
  {"indirizzo abitazione": "Via dei Colli, 123, 35036 Montegrotto Terme PD", "lat": 45.32600, "lon": 11.78400},
  {"indirizzo abitazione": "Via Terme, 156, 35036 Montegrotto Terme PD", "lat": 45.32300, "lon": 11.78700},
  {"indirizzo abitazione": "Via Venezia, 234, 35031 Abano Terme PD", "lat": 45.35800, "lon": 11.79200},
  {"indirizzo abitazione": "Via Milano, 345, 35031 Abano Terme PD", "lat": 45.35700, "lon": 11.79300},
  {"indirizzo abitazione": "Via Torino, 67, 35031 Abano Terme PD", "lat": 45.35900, "lon": 11.79100},
  {"indirizzo abitazione": "Via Firenze, 89, 35031 Abano Terme PD", "lat": 45.35600, "lon": 11.79400},
  {"indirizzo abitazione": "Via Napoli, 123, 35031 Abano Terme PD", "lat": 45.36000, "lon": 11.79000},
  {"indirizzo abitazione": "Via Bologna, 156, 35031 Abano Terme PD", "lat": 45.35500, "lon": 11.79500},
  {"indirizzo abitazione": "Via Genova, 234, 35031 Abano Terme PD", "lat": 45.36100, "lon": 11.78900},
  {"indirizzo abitazione": "Via Palermo, 345, 35031 Abano Terme PD", "lat": 45.35400, "lon": 11.79600},
  {"indirizzo abitazione": "Via Bari, 67, 35031 Abano Terme PD", "lat": 45.36200, "lon": 11.78800},
  {"scuola": "Istituto Comprensivo Limena, Via Roma, 45, 35010 Limena PD", "lat": 45.48200, "lon": 11.82900},
  {"scuola": "Istituto Comprensivo Noventa, Via Roma, 45, 35027 Noventa Padovana PD", "lat": 45.41300, "lon": 11.95900},
  {"scuola": "Istituto Comprensivo Saonara, Via Roma, 45, 35020 Saonara PD", "lat": 45.33700, "lon": 11.97900},
  {"scuola": "Istituto Comprensivo Ponte San Nicolò, Via Roma, 45, 35020 Ponte San Nicolò PD", "lat": 45.37800, "lon": 11.93900},
  {"scuola": "Istituto Comprensivo Pianiga, Via Roma, 45, 35010 Pianiga PD", "lat": 45.41900, "lon": 12.03900},
  {"scuola": "Istituto Comprensivo Albignasego, Via Roma, 45, 35020 Albignasego PD", "lat": 45.34200, "lon": 11.87900},
  {"scuola": "Istituto Comprensivo Selvazzano, Via Roma, 45, 35030 Selvazzano Dentro PD", "lat": 45.38600, "lon": 11.78900},
  {"scuola": "Istituto Comprensivo Rubano, Via Roma, 45, 35030 Rubano PD", "lat": 45.43100, "lon": 11.79900},
  {"scuola": "Istituto Comprensivo Cadoneghe, Via Roma, 45, 35010 Cadoneghe PD", "lat": 45.44800, "lon": 11.93900},
  {"scuola": "Istituto Comprensivo Vigonza, Via Roma, 45, 35010 Vigonza PD", "lat": 45.43600, "lon": 11.96900},
  {"scuola": "Istituto Comprensivo Campodoro, Via Roma, 45, 35010 Campodoro PD", "lat": 45.52200, "lon": 11.82900},
  {"scuola": "Istituto Comprensivo Campo San Martino, Via Roma, 45, 35010 Campo San Martino PD", "lat": 45.52600, "lon": 11.86900},
  {"scuola": "Istituto Comprensivo Cittadella, Via Roma, 45, 35013 Cittadella PD", "lat": 45.64700, "lon": 11.78900},
  {"scuola": "Istituto Comprensivo Camposampiero, Via Roma, 45, 35012 Camposampiero PD", "lat": 45.57300, "lon": 11.93900},
  {"impianto sportivo": "Centro Sportivo Limena, Via dello Sport, 35010 Limena PD", "lat": 45.48700, "lon": 11.83500},
  {"impianto sportivo": "Campo Sportivo Noventa, Via dello Sport, 35027 Noventa Padovana PD", "lat": 45.41800, "lon": 11.96500},
  {"impianto sportivo": "Palestra Saonara, Via dello Sport, 35020 Saonara PD", "lat": 45.34200, "lon": 11.98500},
  {"impianto sportivo": "Centro Sportivo Selvazzano, Via dello Sport, 35030 Selvazzano Dentro PD", "lat": 45.39100, "lon": 11.79500},
  {"impianto sportivo": "Campo Sportivo Rubano, Via dello Sport, 35030 Rubano PD", "lat": 45.43600, "lon": 11.80500},
  {"impianto lavorativo": "Polo Tecnologico Limena, Via Industria, 35010 Limena PD", "lat": 45.48500, "lon": 11.84000},
  {"impianto lavorativo": "Zona Artigianale Noventa, Via Industria, 35027 Noventa Padovana PD", "lat": 45.41600, "lon": 11.97000},
  {"impianto lavorativo": "Centro Commerciale Saonara, Via Industria, 35020 Saonara PD", "lat": 45.34000, "lon": 11.99000},
  {"impianto lavorativo": "Polo Logistico Selvazzano, Via Industria, 35030 Selvazzano Dentro PD", "lat": 45.38900, "lon": 11.80000},
  {"impianto lavorativo": "Zona Industriale Rubano, Via Industria, 35030 Rubano PD", "lat": 45.43400, "lon": 11.81000},
  {"rsa": "Casa di Riposo Limena, Via Roma, 189, 35010 Limena PD", "lat": 45.48700, "lon": 11.83200},
  {"rsa": "RSA Noventa, Via Roma, 189, 35027 Noventa Padovana PD", "lat": 45.41800, "lon": 11.96200},
  {"rsa": "Casa di Riposo Saonara, Via Roma, 189, 35020 Saonara PD", "lat": 45.34200, "lon": 11.98200},
  {"rsa": "RSA Selvazzano, Via Roma, 189, 35030 Selvazzano Dentro PD", "lat": 45.39100, "lon": 11.79200},
  {"rsa": "Casa di Riposo Rubano, Via Roma, 189, 35030 Rubano PD", "lat": 45.43600, "lon": 11.80200},
  {"strada": "A57 Tangenziale di Mestre, km 15, 35010 Limena PD", "lat": 45.49000, "lon": 11.83000},
  {"strada": "SS 308 di Castelfranco e di Bassano, km 45, 35027 Noventa Padovana PD", "lat": 45.42000, "lon": 11.96000},
  {"strada": "A13 Autostrada Bologna-Padova, km 135, 35020 Saonara PD", "lat": 45.34000, "lon": 11.98000},
  {"strada": "A4 Serenissima, km 285, 35020 Ponte San Nicolò PD", "lat": 45.38000, "lon": 11.94000},
  {"strada": "SS 516 Piovese, km 25, 35010 Pianiga PD", "lat": 45.42000, "lon": 12.04000},
  {"strada": "A13 Autostrada Bologna-Padova, km 125, 35020 Albignasego PD", "lat": 45.34000, "lon": 11.88000},
  {"strada": "SS 250 Piovese, km 15, 35030 Selvazzano Dentro PD", "lat": 45.39000, "lon": 11.79000},
  {"strada": "A4 Serenissima, km 275, 35030 Rubano PD", "lat": 45.43000, "lon": 11.80000},
  {"strada": "SS 308 di Castelfranco e di Bassano, km 55, 35010 Cadoneghe PD", "lat": 45.45000, "lon": 11.94000},
  {"strada": "A4 Serenissima, km 295, 35010 Vigonza PD", "lat": 45.44000, "lon": 11.97000},
  {"strada": "SS 307 del Santo, km 35, 35010 Campodoro PD", "lat": 45.52000, "lon": 11.83000},
  {"strada": "A4 Serenissima, km 305, 35010 Campo San Martino PD", "lat": 45.53000, "lon": 11.87000},
  {"strada": "SS 307 del Santo, km 45, 35013 Cittadella PD", "lat": 45.65000, "lon": 11.79000},
  {"strada": "A4 Serenissima, km 315, 35012 Camposampiero PD", "lat": 45.57000, "lon": 11.94000},
  {"strada": "SS 308 di Castelfranco e di Bassano, km 65, 35014 Fontaniva PD", "lat": 45.64000, "lon": 11.75000},
  {"strada": "A4 Serenissima, km 325, 35015 Galliera Veneta PD", "lat": 45.66000, "lon": 11.82000},
  {"strada": "SS 307 del Santo, km 55, 35016 Piazzola sul Brenta PD", "lat": 45.55000, "lon": 11.77000},
  {"strada": "A4 Serenissima, km 335, 35017 San Giorgio delle Pertiche PD", "lat": 45.53000, "lon": 11.92000},
  {"strada": "SS 308 di Castelfranco e di Bassano, km 75, 35018 San Martino di Lupari PD", "lat": 45.69000, "lon": 11.88000},
  {"strada": "A4 Serenissima, km 345, 35019 Tombolo PD", "lat": 45.64000, "lon": 11.79000},
  {"strada": "SS 307 del Santo, km 65, 35020 Due Carrare PD", "lat": 45.29000, "lon": 11.83000},
  {"strada": "A13 Autostrada Bologna-Padova, km 115, 35021 Agna PD", "lat": 45.19000, "lon": 11.96000},
  {"strada": "SS 516 Piovese, km 35, 35022 Arre PD", "lat": 45.22000, "lon": 11.93000},
  {"strada": "A13 Autostrada Bologna-Padova, km 105, 35023 Bagnoli di Sopra PD", "lat": 45.17000, "lon": 11.89000},
  {"strada": "SS 516 Piovese, km 45, 35024 Barbona PD", "lat": 45.20000, "lon": 11.85000},
  {"strada": "A13 Autostrada Bologna-Padova, km 95, 35025 Bovolenta PD", "lat": 45.22000, "lon": 11.85000},
  {"strada": "SS 516 Piovese, km 55, 35026 Candiana PD", "lat": 45.25000, "lon": 11.93000},
  {"strada": "A13 Autostrada Bologna-Padova, km 85, 35028 Piove di Sacco PD", "lat": 45.30000, "lon": 12.03000},
  {"strada": "SS 516 Piovese, km 65, 35029 Pontelongo PD", "lat": 45.23000, "lon": 11.98000},
  {"strada": "A13 Autostrada Bologna-Padova, km 75, 35030 Sant'Angelo di Piove PD", "lat": 45.27000, "lon": 12.01000},
  {"strada": "SS 516 Piovese, km 75, 35032 Sant'Urbano PD", "lat": 45.15000, "lon": 11.63000},
  { "Pronto Soccorso ": "H Cittadella, 35013 Cittadella PD", "lat": 45.6474941, "lon": 11.7886564 },
  { "Pronto Soccorso ": "H Schiavonia, 35043 Monselice PD", "lat": 45.2061159, "lon": 11.7216594 },
  { "Pronto Soccorso ": "H Piove di Sacco, 35028 Piove di Sacco PD", "lat": 45.2928345, "lon": 12.0295599 }
]
